.gitignore
MANIFEST.in
README.rst
bootstrap.py
buildout.cfg
setup.py
collective/__init__.py
collective.js.jcarousel.egg-info/PKG-INFO
collective.js.jcarousel.egg-info/SOURCES.txt
collective.js.jcarousel.egg-info/dependency_links.txt
collective.js.jcarousel.egg-info/entry_points.txt
collective.js.jcarousel.egg-info/namespace_packages.txt
collective.js.jcarousel.egg-info/not-zip-safe
collective.js.jcarousel.egg-info/requires.txt
collective.js.jcarousel.egg-info/top_level.txt
collective/js/__init__.py
collective/js/jcarousel/__init__.py
collective/js/jcarousel/configure.zcml
collective/js/jcarousel/interfaces.py
collective/js/jcarousel/profiles/default/jsregistry.xml
collective/js/jcarousel/profiles/default/metadata.xml
collective/js/jcarousel/resources/style.css
collective/js/jcarousel/resources/lib/jquery.jcarousel.js
collective/js/jcarousel/resources/lib/jquery.jcarousel.min.js
collective/js/jcarousel/resources/skins/ie7/credits.txt
collective/js/jcarousel/resources/skins/ie7/loading-small.gif
collective/js/jcarousel/resources/skins/ie7/loading.gif
collective/js/jcarousel/resources/skins/ie7/loading_small.gif
collective/js/jcarousel/resources/skins/ie7/next-horizontal.gif
collective/js/jcarousel/resources/skins/ie7/prev-horizontal.gif
collective/js/jcarousel/resources/skins/ie7/skin.css
collective/js/jcarousel/resources/skins/tango/credits.txt
collective/js/jcarousel/resources/skins/tango/next-horizontal.png
collective/js/jcarousel/resources/skins/tango/next-vertical.png
collective/js/jcarousel/resources/skins/tango/prev-horizontal.png
collective/js/jcarousel/resources/skins/tango/prev-vertical.png
collective/js/jcarousel/resources/skins/tango/skin.css
docs/HISTORY.txt