Metadata-Version: 1.0
Name: collective.js.jcarousel
Version: 1.0
Summary: JCarousel registration in Plone resource registry
Home-page: https://github.com/collective/collective.js.jcarousel
Author: JeanMichel FRANCOIS aka toutpt
Author-email: toutpt@gmail.com
License: GPL
Platform: UNKNOWN
Classifier: Programming Language :: Python
